{
    "buttons": [
        {
            "id": "copy_paste_enter",
            "label": "Copy, Paste & Enter",
            "action": "copy_paste_and_enter",
            "key_sequence": {
                "windows": [
                    {
                        "key": "ctrl",
                        "action": "down"
                    },
                    {
                        "key": "v",
                        "action": "press"
                    },
                    {
                        "key": "ctrl",
                        "action": "up"
                    },
                    {
                        "key": "enter",
                        "action": "press"
                    }
                ],
                "macos": [
                    {
                        "key": "cmd",
                        "action": "down"
                    },
                    {
                        "key": "v",
                        "action": "press"
                    },
                    {
                        "key": "cmd",
                        "action": "up"
                    },
                    {
                        "key": "enter",
                        "action": "press"
                    }
                ],
                "linux": [
                    {
                        "key": "ctrl",
                        "action": "down"
                    },
                    {
                        "key": "v",
                        "action": "press"
                    },
                    {
                        "key": "ctrl",
                        "action": "up"
                    },
                    {
                        "key": "enter",
                        "action": "press"
                    }
                ]
            }
        },
        {
            "id": "accept",
            "label": "Accept",
            "action": "simulate_key_sequence",
            "key_sequence": {
                "windows": [
                    {
                        "key": "ctrl",
                        "action": "down"
                    },
                    {
                        "key": "enter",
                        "action": "press"
                    },
                    {
                        "key": "ctrl",
                        "action": "up"
                    }
                ],
                "macos": [
                    {
                        "key": "cmd",
                        "action": "down"
                    },
                    {
                        "key": "enter",
                        "action": "press"
                    },
                    {
                        "key": "cmd",
                        "action": "up"
                    }
                ],
                "linux": [
                    {
                        "key": "ctrl",
                        "action": "down"
                    },
                    {
                        "key": "enter",
                        "action": "press"
                    },
                    {
                        "key": "ctrl",
                        "action": "up"
                    }
                ]
            }
        },
        {
            "id": "new",
            "label": "New",
            "action": "simulate_key_sequence",
            "key_sequence": {
                "windows": [
                    {
                        "key": "ctrl",
                        "action": "down"
                    },
                    {
                        "key": "n",
                        "action": "press"
                    },
                    {
                        "key": "ctrl",
                        "action": "up"
                    }
                ],
                "macos": [
                    {
                        "key": "cmd",
                        "action": "down"
                    },
                    {
                        "key": "n",
                        "action": "press"
                    },
                    {
                        "key": "cmd",
                        "action": "up"
                    }
                ],
                "linux": [
                    {
                        "key": "ctrl",
                        "action": "down"
                    },
                    {
                        "key": "n",
                        "action": "press"
                    },
                    {
                        "key": "ctrl",
                        "action": "up"
                    }
                ]
            }
        },
        {
            "id": "stop",
            "label": "Stop",
            "action": "simulate_key_sequence",
            "classes": "bg-red-500",
            "key_sequence": {
                "windows": [
                    {
                        "key": "ctrl",
                        "action": "down"
                    },
                    {
                        "key": "shift",
                        "action": "down"
                    },
                    {
                        "key": "backspace",
                        "action": "press"
                    },
                    {
                        "key": "shift",
                        "action": "up"
                    },
                    {
                        "key": "ctrl",
                        "action": "up"
                    }
                ],
                "macos": [
                    {
                        "key": "cmd",
                        "action": "down"
                    },
                    {
                        "key": "shift",
                        "action": "down"
                    },
                    {
                        "key": "backspace",
                        "action": "press"
                    },
                    {
                        "key": "shift",
                        "action": "up"
                    },
                    {
                        "key": "cmd",
                        "action": "up"
                    }
                ],
                "linux": [
                    {
                        "key": "ctrl",
                        "action": "down"
                    },
                    {
                        "key": "shift",
                        "action": "down"
                    },
                    {
                        "key": "backspace",
                        "action": "press"
                    },
                    {
                        "key": "shift",
                        "action": "up"
                    },
                    {
                        "key": "ctrl",
                        "action": "up"
                    }
                ]
            }
        },
        {
            "id": "reject",
            "label": "Reject",
            "action": "simulate_key_sequence",
            "classes": "bg-red-500",
            "key_sequence": {
                "windows": [
                    {
                        "key": "ctrl",
                        "action": "down"
                    },
                    {
                        "key": "backspace",
                        "action": "press"
                    },
                    {
                        "key": "ctrl",
                        "action": "up"
                    }
                ],
                "macos": [
                    {
                        "key": "cmd",
                        "action": "down"
                    },
                    {
                        "key": "backspace",
                        "action": "press"
                    },
                    {
                        "key": "cmd",
                        "action": "up"
                    }
                ],
                "linux": [
                    {
                        "key": "ctrl",
                        "action": "down"
                    },
                    {
                        "key": "backspace",
                        "action": "press"
                    },
                    {
                        "key": "ctrl",
                        "action": "up"
                    }
                ]
            }
        },
        {
            "id": "clear",
            "label": "Clear",
            "action": "clear_text",
            "classes": "bg-red-500",
            "key_sequence": null
        },
        {
            "id": "copy",
            "label": "Copy",
            "action": "copy_text",
            "key_sequence": {
                "windows": [
                    {
                        "key": "ctrl",
                        "action": "down"
                    },
                    {
                        "key": "c",
                        "action": "press"
                    },
                    {
                        "key": "ctrl",
                        "action": "up"
                    }
                ],
                "macos": [
                    {
                        "key": "cmd",
                        "action": "down"
                    },
                    {
                        "key": "c",
                        "action": "press"
                    },
                    {
                        "key": "cmd",
                        "action": "up"
                    }
                ],
                "linux": [
                    {
                        "key": "ctrl",
                        "action": "down"
                    },
                    {
                        "key": "c",
                        "action": "press"
                    },
                    {
                        "key": "ctrl",
                        "action": "up"
                    }
                ]
            }
        },
        {
            "id": "paste",
            "label": "Paste",
            "action": "simulate_key_sequence",
            "key_sequence": {
                "windows": [
                    {
                        "key": "ctrl",
                        "action": "down"
                    },
                    {
                        "key": "v",
                        "action": "press"
                    },
                    {
                        "key": "ctrl",
                        "action": "up"
                    }
                ],
                "macos": [
                    {
                        "key": "cmd",
                        "action": "down"
                    },
                    {
                        "key": "v",
                        "action": "press"
                    },
                    {
                        "key": "cmd",
                        "action": "up"
                    }
                ],
                "linux": [
                    {
                        "key": "ctrl",
                        "action": "down"
                    },
                    {
                        "key": "v",
                        "action": "press"
                    },
                    {
                        "key": "ctrl",
                        "action": "up"
                    }
                ]
            }
        },
        {
            "id": "copy_paste",
            "label": "Copy & Paste",
            "action": "copy_and_paste",
            "key_sequence": {
                "windows": [
                    {
                        "key": "ctrl",
                        "action": "down"
                    },
                    {
                        "key": "v",
                        "action": "press"
                    },
                    {
                        "key": "ctrl",
                        "action": "up"
                    }
                ],
                "macos": [
                    {
                        "key": "cmd",
                        "action": "down"
                    },
                    {
                        "key": "v",
                        "action": "press"
                    },
                    {
                        "key": "cmd",
                        "action": "up"
                    }
                ],
                "linux": [
                    {
                        "key": "ctrl",
                        "action": "down"
                    },
                    {
                        "key": "v",
                        "action": "press"
                    },
                    {
                        "key": "ctrl",
                        "action": "up"
                    }
                ]
            }
        },
        {
            "id": "enter",
            "label": "Enter",
            "action": "simulate_key_sequence",
            "key_sequence": {
                "windows": [
                    {
                        "key": "enter",
                        "action": "press"
                    }
                ],
                "macos": [
                    {
                        "key": "enter",
                        "action": "press"
                    }
                ],
                "linux": [
                    {
                        "key": "enter",
                        "action": "press"
                    }
                ]
            }
        }
    ]
}